bebleo_smtpd_fixture/__init__.py
bebleo_smtpd_fixture/authenticator.py
bebleo_smtpd_fixture/config.py
bebleo_smtpd_fixture/controller.py
bebleo_smtpd_fixture/fixture.py
bebleo_smtpd_fixture/handlers.py
bebleo_smtpd_fixture/smtp.py
bebleo_smtpd_fixture/certs/cert.pem
bebleo_smtpd_fixture/certs/key.pem
bebleo_smtpd_fixture-0.2.3.dist-info/LICENSE
bebleo_smtpd_fixture-0.2.3.dist-info/METADATA
bebleo_smtpd_fixture-0.2.3.dist-info/WHEEL
bebleo_smtpd_fixture-0.2.3.dist-info/top_level.txt
bebleo_smtpd_fixture-0.2.3.dist-info/RECORD
