Metadata-Version: 2.1
Name: bebleo-smtpd-fixture
Version: 0.2.3
Summary: A mock SMTP server designed for use as a test fixture that implements encryption and authentication to mimic a real world server.
Home-page: https://github.com/bebleo/bebleo-smtpd-fixture
Author: James Warne
Author-email: bebleo@yahoo.com
License: UNKNOWN
Platform: UNKNOWN
Classifier: Programming Language :: Python :: 3
Classifier: Programming Language :: Python :: 3.6
Classifier: Programming Language :: Python :: 3.7
Classifier: Programming Language :: Python :: 3.8
Classifier: License :: OSI Approved :: MIT License
Classifier: Operating System :: OS Independent
Requires-Python: >=3.6
Requires-Dist: aiosmtpd
Requires-Dist: python-dotenv (<=0.14.0)
Requires-Dist: pytest
